sas_kernel/Readme.md
sas_kernel/__init__.py
sas_kernel/__main__.py
sas_kernel/install.py
sas_kernel/kernel.py
sas_kernel/version.py
sas_kernel/data/__init__.py
sas_kernel/data/logo-64x64.png
sas_kernel/data/sasgrammardictionary.json
sas_kernel/data/sasgrammerdictionary.json
sas_kernel/data/sasproclist.json
sas_kernel/doc/__init__.py
sas_kernel/doc/source/__init__.py
sas_kernel/doc/source/conf.py
sas_kernel/magics/README.md
sas_kernel/magics/__init__.py
sas_kernel/magics/log_magic.py
sas_kernel/magics/prompt4var_magic.py
sas_kernel/showSASLog/__init__.py
sas_kernel/showSASLog/main.js
sas_kernel/showSASLog/readme.md
sas_kernel/showSASLog/showSASLog.yaml
sas_kernel/theme/__init__.py
sas_kernel/theme/base16-sas-light.css
sas_kernel/theme/readme.md
sas_kernel/theme/theme_selector.js
sas_kernel/theme/theme_selector.yaml
SAS_kernel-2.4.6.dist-info/LICENSE.txt
SAS_kernel-2.4.6.dist-info/METADATA
SAS_kernel-2.4.6.dist-info/WHEEL
SAS_kernel-2.4.6.dist-info/top_level.txt
SAS_kernel-2.4.6.dist-info/RECORD
