Metadata-Version: 2.1
Name: SAS-kernel
Version: 2.4.6
Summary: A SAS kernel for Jupyter
Home-page: https://github.com/sassoftware/sas_kernel
Author: Jared Dean
Author-email: jared.dean@sas.com
License: Apache Software License
Platform: UNKNOWN
Classifier: Framework :: IPython
Classifier: License :: OSI Approved :: Apache Software License
Classifier: Programming Language :: Python :: 3
Classifier: Programming Language :: Python :: 3.4
Classifier: Programming Language :: Python :: 3.5
Classifier: Programming Language :: Python :: 3.6
Classifier: Programming Language :: Python :: 3.7
Classifier: Programming Language :: Python :: 3.8
Classifier: Intended Audience :: Science/Research
Classifier: Intended Audience :: Developers
Classifier: Operating System :: OS Independent
Classifier: Topic :: Software Development
Classifier: Topic :: System :: Shells
Requires-Dist: saspy (>=3.6)
Requires-Dist: metakernel (>=0.27.5)
Requires-Dist: jupyter-client (>=6)
Requires-Dist: ipython (>=7)
Provides-Extra: jlab_ext
Requires-Dist: jupyterlab (>=3) ; extra == 'jlab_ext'
Requires-Dist: jlab-create-sas-file ; extra == 'jlab_ext'
